vegalib-0.1.1.dist-info/METADATA
vegalib-0.1.1.dist-info/WHEEL
vegalib-0.1.1.dist-info/licenses/LICENSE
vegalib/__init__.py
vegalib/bar.py
vegalib/vegalib.cpython-312-darwin.so
vegalib-0.1.1.dist-info/RECORD
