Metadata-Version: 2.4
Name: vegalib
Version: 0.1.1
Classifier: Programming Language :: Rust
Classifier: Programming Language :: Python :: Implementation :: CPython
Classifier: Programming Language :: Python :: Implementation :: PyPy
License-File: LICENSE
Summary: A small library for derivatives pricing
Author: jmishin
License: MIT
Requires-Python: >=3.10
